.gitignore
LICENSE
README.md
TODO
requirements.txt
setup.py
examples/MMR.py
examples/MMR_Plots.py
examples/exp_example.png
examples/exp_example.py
mbam/__init__.py
mbam/auto_diff.py
mbam/finite_difference.py
mbam/geodesic.py
mbam/utils.py
mbam.egg-info/PKG-INFO
mbam.egg-info/SOURCES.txt
mbam.egg-info/dependency_links.txt
mbam.egg-info/requires.txt
mbam.egg-info/top_level.txt
tests/model_exp.py
tests/model_linear.py
tests/test_auto_diff.py
tests/test_finite_diff.py
tests/test_geodesic.py
tests/test_initial_velocity.py