Metadata-Version: 2.1
Name: mbam
Version: 0.1.0
Summary: Code for the Manifold Boundary Approximation Method
Home-page: https://github.com/mktranstrum/MBAM
Author: Mark K. Transtrum
Author-email: mktranstrum@byu.edu
Maintainer: Yonatan Kurniawan
Maintainer-email: kurniawanyo@outlook.com
License: UNKNOWN
Platform: UNKNOWN
Classifier: Programming Language :: Python :: 3
Requires-Python: >=3.6
License-File: LICENSE
